nanokontrol_config/__init__.py
nanokontrol_config/cli.py
nanokontrol_config/nanokontrol_studio.py
nanokontrol_config-0.4.0.dist-info/METADATA
nanokontrol_config-0.4.0.dist-info/WHEEL
nanokontrol_config-0.4.0.dist-info/entry_points.txt
nanokontrol_config-0.4.0.dist-info/RECORD
