Metadata-Version: 2.4
Name: nanokontrol-config
Version: 0.4.0
Summary: Configuration tool for Korg nanoKontrol Studio
Project-URL: Repository, https://github.com/frans-fuerst/nanokontrol-config.git
Author-email: Frans Fürst <frans.fuerst+gitlab@protonmail.com>
Requires-Python: <3.14,>=3.12
Requires-Dist: mido>=1.3.3
Requires-Dist: pydantic>=2.11.7
Requires-Dist: python-rtmidi>=1.5.8
Requires-Dist: pyyaml>=6.0.2
